{
  "version": "0.1",
  "id": "noMarketContractGSHT",
  "targetURL": "http://192.168.0.200:8080/ptsoa/forms/pt/PO_CONTRACT2_INFO/contract_add.htm?_objName=PO_CONTRACT2_INFO&_defKey=po_contract2&_defId=po_contract2:1:24810f12-9cc3-4676-8ead-5e1dc0af3dca&_instId=f5605da5-a448-4bbe-aa1b-358fabdd7670&_taskId=574f2871-b084-498d-bd45-25bac0abb812&_nodeId=UserTask_2&_agent=&_pk=UUID&_pkValue=bddb8bd24101f8eddc0ae84d9636ac89&_useType=modify",
  "jsFile": "../../lib/base.js,index.js",
  "cssFile": "index.css,../../lib/base.css",
  "chineseName": "非采购流程格式合同",
  "description": "",
  "controls": {
    "control22": {
      "location": {
        "data": {
          "tagName": "KBD"
        },
        "locators": [
          {
            "id": "button/text",
            "prob": 3,
            "value": {
              "text": [
                "附件:"
              ],
              "visText": [
                "附件:"
              ]
            }
          },
          {
            "id": "text",
            "prob": 3,
            "value": {
              "text": [
                "附件:"
              ],
              "visText": [
                "附件:"
              ]
            }
          },
          {
            "id": "@id/word",
            "prob": 2,
            "value": [
              "descendant::DIV[@id=\"tabs\"]//DIV[@id=\"content_baseinfo\"]/TABLE[1]/TBODY[1]/TR[11]/TD[1]/KBD[1]",
              "descendant::DIV[@id=\"content_baseinfo\"]/TABLE[1]/TBODY[1]/TR[11]/TD[1]/KBD[1]"
            ]
          },
          {
            "id": "@class/word",
            "prob": 1,
            "ordinal": [
              26,
              27
            ],
            "value": "DIV.ui-tab-form-content TABLE.ui-table-A TD.title-r KBD"
          },
          {
            "id": "path/ordinal",
            "prob": 1,
            "value": "/HTML[1]/BODY[1]/DIV[1]/DIV[1]/DIV[4]/DIV[1]/TABLE[1]/TBODY[1]/TR[11]/TD[1]/KBD[1]"
          },
          {
            "id": "elderLevel",
            "value": {
              "level": 0
            }
          },
          {
            "id": "shield",
            "value": {
              "zIndex": "auto",
              "width": 33.1875,
              "height": 16
            }
          }
        ]
      },
      "roles": "element",
      "text": "附件:"
    },
    "control23": {
      "location": {
        "data": {
          "tagName": "LABEL"
        },
        "locators": [
          {
            "id": "button/text",
            "prob": 3,
            "value": {
              "text": [
                "非采销合同"
              ],
              "visText": [
                "非采销合同"
              ]
            }
          },
          {
            "id": "text",
            "prob": 3,
            "value": {
              "text": [
                "非采销合同"
              ],
              "visText": [
                "非采销合同"
              ]
            }
          },
          {
            "id": "@id/word",
            "prob": 3,
            "value": "descendant::LABEL[@id=\"funcName\"]"
          },
          {
            "id": "@class/word",
            "prob": 1,
            "value": "DIV.tpl-form-border DIV.tpl-form-new H1 LABEL"
          },
          {
            "id": "path/ordinal",
            "prob": 1,
            "value": "/HTML[1]/BODY[1]/DIV[1]/DIV[1]/DIV[1]/H1[1]/LABEL[1]"
          },
          {
            "id": "elderLevel",
            "value": {
              "level": 0
            }
          },
          {
            "id": "shield",
            "value": {
              "zIndex": "auto",
              "width": 106,
              "height": 36
            }
          }
        ]
      },
      "events": {
        "onGetData": "getData_control23"
      },
      "intendedRole": "custom",
      "roles": "element,custom",
      "monitored": false
    },
    "control24": {
      "location": {
        "data": {
          "tagName": "TBODY"
        },
        "locators": [
          {
            "id": "@id/word",
            "prob": 2,
            "value": [
              "descendant::DIV[@id=\"tabs\"]//DIV[@id=\"content_baseinfo\"]/TABLE[1]/TBODY[1]",
              "descendant::DIV[@id=\"tabs\"]//DIV[@id=\"content_baseinfo\"]//TBODY",
              "descendant::DIV[@id=\"content_baseinfo\"]//TBODY"
            ]
          },
          {
            "id": "@class/word",
            "prob": 1,
            "ordinal": [
              0,
              2
            ],
            "value": "DIV.tpl-form-new DIV.ui-tab-form-content TABLE.ui-table-A TBODY"
          },
          {
            "id": "path/ordinal",
            "prob": 1,
            "value": "/HTML[1]/BODY[1]/DIV[1]/DIV[1]/DIV[4]/DIV[1]/TABLE[1]/TBODY[1]"
          },
          {
            "id": "shield",
            "value": {
              "zIndex": "auto",
              "width": 1383,
              "height": 339
            }
          }
        ]
      },
      "events": {
        "onGetData": "getData_control24"
      },
      "intendedRole": "custom",
      "roles": "element,link,custom",
      "monitored": true
    },
    "control21": {
      "location": {
        "data": {
          "tagName": "SPAN"
        },
        "locators": [
          {
            "id": "button/text",
            "prob": 3,
            "value": {
              "text": [
                "提交"
              ],
              "visText": [
                "提交"
              ]
            }
          },
          {
            "id": "text",
            "prob": 3,
            "value": {
              "text": [
                "提交"
              ],
              "visText": [
                "提交"
              ]
            }
          },
          {
            "id": "@id/word",
            "prob": 2,
            "value": [
              "descendant::DIV[@id=\"tool-box\"]/DIV[1]/A[1]/SPAN[1]",
              "descendant::DIV[@id=\"tool-box\"]//SPAN"
            ]
          },
          {
            "id": "@class/word",
            "prob": 1,
            "ordinal": [
              0,
              4
            ],
            "value": "DIV.tpl-form-new DIV.tpl-toolbar-new DIV.ui-button-FixCS A SPAN"
          },
          {
            "id": "path/ordinal",
            "prob": 1,
            "value": "/HTML[1]/BODY[1]/DIV[1]/DIV[1]/DIV[2]/DIV[1]/A[1]/SPAN[1]"
          },
          {
            "id": "shield",
            "value": {
              "zIndex": "auto",
              "width": 81,
              "height": 24
            }
          }
        ]
      },
      "intendedRole": "button",
      "roles": "element,button",
      "monitored": false
    },
    "control25": {
      "location": {
        "data": {
          "tagName": "SPAN"
        },
        "locators": [
          {
            "id": "button/text",
            "prob": 3,
            "value": {
              "text": [
                "终止"
              ],
              "visText": [
                "终止"
              ]
            }
          },
          {
            "id": "text",
            "prob": 3,
            "value": {
              "text": [
                "终止"
              ],
              "visText": [
                "终止"
              ]
            }
          },
          {
            "id": "@id/word",
            "prob": 2,
            "value": [
              "descendant::DIV[@id=\"tool-box\"]/DIV[3]/A[1]/SPAN[1]",
              "descendant::DIV[@id=\"tool-box\"]//SPAN"
            ]
          },
          {
            "id": "@class/word",
            "prob": 1,
            "ordinal": [
              2,
              4
            ],
            "value": "DIV.tpl-form-new DIV.tpl-toolbar-new DIV.ui-button-FixCS A SPAN"
          },
          {
            "id": "path/ordinal",
            "prob": 1,
            "value": "/HTML[1]/BODY[1]/DIV[1]/DIV[1]/DIV[2]/DIV[3]/A[1]/SPAN[1]"
          },
          {
            "id": "shield",
            "value": {
              "zIndex": "auto",
              "width": 81,
              "height": 24
            }
          }
        ]
      },
      "intendedRole": "button",
      "roles": "element,button",
      "monitored": false
    },
    "control26": {
      "location": {
        "data": {
          "tagName": "INPUT"
        },
        "locators": [
          {
            "id": "elem/@name",
            "prob": 2,
            "value": "descendant::INPUT[@name=\"fileName\"]"
          },
          {
            "id": "@id/word",
            "prob": 4,
            "value": [
              "descendant::DIV[@id=\"content_baseinfo\"]//DIV[@id=\"fileupload\"]//INPUT[@id=\"file\"]",
              "descendant::DIV[@id=\"fileupload\"]//INPUT[@id=\"file\"]",
              "descendant::INPUT[@id=\"file\"]"
            ]
          },
          {
            "id": "@class/word",
            "prob": 1,
            "value": "DIV.ui-widget DIV.fileupload-buttonbar.ui-widget-header.ui-corner-top LABEL.fileinput-button.ui-button.ui-widget.ui-state-default.ui-corner-all.ui-button-text-icon-primary INPUT"
          },
          {
            "id": "path/ordinal",
            "prob": 1,
            "value": "/HTML[1]/BODY[1]/DIV[1]/DIV[1]/DIV[4]/DIV[1]/TABLE[1]/TBODY[1]/TR[11]/TD[2]/SPAN[1]/DIV[1]/FORM[1]/DIV[1]/LABEL[1]/INPUT[1]"
          },
          {
            "id": "input/type",
            "verifyEnabled": true,
            "value": "file"
          },
          {
            "id": "elderLevel",
            "value": {
              "level": 0
            }
          },
          {
            "id": "shield",
            "value": {
              "zIndex": "0",
              "width": 460,
              "height": 118
            }
          }
        ]
      },
      "events": {
        "onGetData": "getData_control26"
      },
      "intendedRole": "custom",
      "roles": "element,file,custom",
      "ignoreVisibility": true,
      "monitored": false
    },
    "control27": {
      "location": {
        "data": {
          "tagName": "TBODY"
        },
        "locators": [
          {
            "id": "text",
            "prob": 3,
            "value": {
              "text": [
                "QQ20161104-0@2x.png删除QQ20161104-0@2x.png删除"
              ],
              "visText": [
                "QQ20161104-0@2x.png 删除 QQ20161104-0@2x.png 删除"
              ]
            }
          },
          {
            "id": "@id/word",
            "prob": 2,
            "value": [
              "descendant::DIV[@id=\"tabs\"]//DIV[@id=\"content_baseinfo\"]//DIV[@id=\"fileupload\"]/DIV[1]/TABLE[1]/TBODY[1]",
              "descendant::DIV[@id=\"tabs\"]//DIV[@id=\"content_baseinfo\"]//DIV[@id=\"fileupload\"]//TBODY",
              "descendant::DIV[@id=\"content_baseinfo\"]//DIV[@id=\"fileupload\"]//TBODY",
              "descendant::DIV[@id=\"fileupload\"]//TBODY"
            ]
          },
          {
            "id": "@class/word",
            "prob": 1,
            "value": "DIV.ui-widget DIV.fileupload-content.ui-widget-content.ui-corner-bottom TABLE.files TBODY"
          },
          {
            "id": "path/ordinal",
            "prob": 1,
            "value": "/HTML[1]/BODY[1]/DIV[1]/DIV[1]/DIV[4]/DIV[1]/TABLE[1]/TBODY[1]/TR[11]/TD[2]/SPAN[1]/DIV[1]/DIV[1]/TABLE[1]/TBODY[1]"
          },
          {
            "id": "shield",
            "value": {
              "zIndex": "auto",
              "width": 222,
              "height": 72
            }
          }
        ]
      },
      "events": {
        "onGetData": "getData_control27"
      },
      "intendedRole": "custom",
      "roles": "element,custom",
      "monitored": true
    }
  },
  "contexts": {
    "context1": {
      "controls": [
        "control23",
        "control24",
        "control21",
        "control25",
        "control26",
        "control27"
      ],
      "anchors": [
        "control22"
      ]
    }
  },
  "flows": {
    "flow9": {
      "toContexts": [
        {
          "toContextId": "context1"
        }
      ]
    },
    "flow11": {
      "fromContextId": "context1",
      "fromAction": "doAction",
      "fromControlId": "control24",
      "toContexts": [
        {
          "toContextId": "context1"
        }
      ]
    },
    "flow13": {
      "fromContextId": "context1",
      "fromAction": "click",
      "fromControlId": "control25",
      "toContexts": [
        {
          "toContextId": "context1"
        }
      ]
    }
  },
  "pages": {
    "page1": {
      "contextId": "context1",
      "layout": [
        {
          "id": "uiControl26",
          "controlId": "control23",
          "display": {
            "adapterId": "custom",
            "type": "custom",
            "adapter": {
              "templateType": "react",
              "events": {
                "onDoAction": "doAction_uiControl26",
                "onGetTemplate": "getTemplate_uiControl26"
              }
            }
          }
        },
        {
          "id": "uiControl27",
          "controlId": "control24",
          "display": {
            "adapterId": "custom",
            "type": "custom",
            "adapter": {
              "templateType": "react",
              "events": {
                "onDoAction": "doAction_uiControl27",
                "onGetTemplate": "getTemplate_uiControl27"
              }
            }
          }
        },
        {
          "id": "uiControl30",
          "display": {
            "type": "sticky",
            "adapterId": "sticky",
            "position": "bottom",
            "adapter": {
              "templateType": ""
            }
          },
          "layout": [
            {
              "id": "uiControl30body",
              "display": {
                "type": "stickyBody",
                "adapterId": "stickyBody",
                "adapter": {
                  "templateType": ""
                }
              },
              "layout": [
                {
                  "id": "uiControl31",
                  "display": {
                    "type": "dialog",
                    "adapterId": "dialog",
                    "actionsButtonText": "操作",
                    "adapter": {
                      "templateType": ""
                    }
                  },
                  "layout": [
                    {
                      "id": "uiControl31body",
                      "display": {
                        "type": "dialogBody",
                        "adapterId": "dialogBody",
                        "adapter": {
                          "templateType": ""
                        }
                      },
                      "layout": [
                        {
                          "id": "uiControl29",
                          "controlId": "control26",
                          "display": {
                            "adapterId": "custom",
                            "type": "custom",
                            "adapter": {
                              "templateType": "react",
                              "events": {
                                "onDoAction": "doAction_uiControl29",
                                "onGetTemplate": "getTemplate_uiControl29"
                              }
                            }
                          }
                        }
                      ]
                    },
                    {
                      "id": "uiControl31footer",
                      "display": {
                        "type": "dialogFooter",
                        "adapterId": "dialogFooter",
                        "adapter": {
                          "templateType": ""
                        }
                      },
                      "layout": [
                        {
                          "id": "uiControl36",
                          "controlId": "control27",
                          "display": {
                            "adapterId": "custom",
                            "type": "custom",
                            "adapter": {
                              "templateType": "react",
                              "events": {
                                "onDoAction": "doAction_uiControl36",
                                "onGetTemplate": "getTemplate_uiControl36"
                              }
                            }
                          }
                        },
                        {
                          "id": "uiControl32",
                          "display": {
                            "type": "card",
                            "adapterId": "card",
                            "adapter": {
                              "templateType": ""
                            }
                          },
                          "layout": [
                            {
                              "id": "uiControl32body",
                              "display": {
                                "type": "cardBody",
                                "adapterId": "cardBody",
                                "adapter": {
                                  "templateType": ""
                                }
                              },
                              "layout": [
                                {
                                  "id": "uiControl33",
                                  "display": {
                                    "type": "grid",
                                    "adapterId": "grid",
                                    "adapter": {
                                      "templateType": ""
                                    }
                                  },
                                  "layout": [
                                    {
                                      "id": "uiControl33row0",
                                      "display": {
                                        "cols": 3,
                                        "type": "col",
                                        "adapterId": "col",
                                        "adapter": {
                                          "templateType": ""
                                        }
                                      },
                                      "layout": [
                                        {
                                          "id": "uiControl34",
                                          "controlId": "control21",
                                          "display": {
                                            "adapterId": "clickable",
                                            "type": "button",
                                            "amStyle": "primary",
                                            "adapter": {
                                              "templateType": ""
                                            }
                                          }
                                        }
                                      ]
                                    },
                                    {
                                      "id": "uiControl33row1",
                                      "display": {
                                        "cols": 3,
                                        "type": "col",
                                        "adapterId": "col",
                                        "adapter": {
                                          "templateType": ""
                                        }
                                      },
                                      "layout": [
                                        {
                                          "id": "uiControl35",
                                          "controlId": "control25",
                                          "display": {
                                            "adapterId": "clickable",
                                            "type": "button",
                                            "adapter": {
                                              "templateType": ""
                                            }
                                          }
                                        }
                                      ]
                                    }
                                  ]
                                }
                              ]
                            }
                          ]
                        }
                      ]
                    }
                  ]
                }
              ]
            }
          ]
        }
      ]
    }
  },
  "matchers": {
    "page/title": {
      "contexts": {
        "context1": [
          ""
        ]
      }
    },
    "page/urls": {
      "contexts": {
        "context1": [
          "192.168.0.200:8080/ptsoa/forms/pt/PO_CONTRACT2_INFO/contract_add.htm?_objName=PO_CONTRACT2_INFO&_defKey=po_contract2&_defId=po_contract2:1:24810f12-9cc3-4676-8ead-5e1dc0af3dca&_instId=f5605da5-a448-4bbe-aa1b-358fabdd7670&_taskId=574f2871-b084-498d-bd45-25bac0abb812&_nodeId=UserTask_2&_agent=&_pk=UUID&_pkValue=bddb8bd24101f8eddc0ae84d9636ac89&_useType=modify",
          "192.168.0.200:8080/ptsoa/forms/pt/PO_CONTRACT2_INFO/contract_add.htm?_objName=PO_CONTRACT2_INFO&_defKey=po_contract2&_defId=po_contract2:1:24810f12-9cc3-4676-8ead-5e1dc0af3dca&_instId=f5605da5-a448-4bbe-aa1b-358fabdd7670&_taskId=874cf4fc-6548-41a7-b928-2552c7796335&_nodeId=UserTask_2&_agent=&_pk=UUID&_pkValue=bddb8bd24101f8eddc0ae84d9636ac89&_useType=modify"
        ]
      }
    },
    "page/ids": {
      "contexts": {
        "context1": [
          [
            "AD_Project_",
            "AD_Project__input",
            "Advance_ProcessStatus",
            "FixJSON",
            "HTMLSelect_",
            "HTMLSelect__FixCOM",
            "HandleCommand_",
            "JQFileUpload_",
            "LABEL_",
            "PO_CONTRACT_INFO_CONTRACT_MONEY",
            "PO_CONTRACT_INFO_CONTRACT_NAME",
            "PO_CONTRACT_INFO_CONTRACT_NUM",
            "PO_CONTRACT_INFO_CONTRACT_OTHER",
            "PO_CONTRACT_INFO_PROCUREMENT_BIDDING_NUM",
            "PO_CONTRACT_INFO_UNDERLYING",
            "_ATTACHMENT_DELETE_IDS_",
            "content_baseinfo",
            "file",
            "fileupload",
            "funcName",
            "input_",
            "tabs",
            "template-download",
            "template-upload",
            "tool-box"
          ],
          [
            "AD_Project_",
            "HTMLSelect_",
            "JQFileUpload_",
            "LABEL_",
            "PO_CONTRACT_INFO_CONTRACT_MONEY",
            "PO_CONTRACT_INFO_CONTRACT_NAME",
            "PO_CONTRACT_INFO_CONTRACT_NUM",
            "PO_CONTRACT_INFO_CONTRACT_OTHER",
            "PO_CONTRACT_INFO_PROCUREMENT_BIDDING_NUM",
            "PO_CONTRACT_INFO_UNDERLYING",
            "content_baseinfo",
            "funcName",
            "input_",
            "tabs",
            "tool-box"
          ],
          [
            "AD_Project_",
            "AD_Project__input",
            "Advance_ProcessStatus",
            "FixJSON",
            "HTMLSelect_",
            "HTMLSelect__FixCOM",
            "HandleCommand_",
            "JQFileUpload_",
            "LABEL_",
            "PO_CONTRACT_INFO_CONTRACT_MONEY",
            "PO_CONTRACT_INFO_CONTRACT_NAME",
            "PO_CONTRACT_INFO_CONTRACT_NUM",
            "PO_CONTRACT_INFO_CONTRACT_OTHER",
            "PO_CONTRACT_INFO_PROCUREMENT_BIDDING_NUM",
            "PO_CONTRACT_INFO_UNDERLYING",
            "_ATTACHMENT_DELETE_IDS_",
            "content_baseinfo",
            "deleteTemp",
            "file",
            "fileupload",
            "funcName",
            "input_",
            "pta",
            "tabs",
            "template-download",
            "template-upload",
            "tool-box"
          ]
        ]
      }
    },
    "page/classes": {
      "contexts": {
        "context1": [
          [
            "fileinput-button",
            "files",
            "fileupload-buttonbar",
            "fileupload-content",
            "fileupload-progressbar",
            "fn-clear",
            "img-",
            "title-r",
            "tpl-form-border",
            "tpl-form-new",
            "tpl-toolbar-new",
            "ui-button",
            "ui-button-FixCS",
            "ui-button-FixCS-small",
            "ui-button-icon-primary",
            "ui-button-text",
            "ui-button-text-icon-primary",
            "ui-corner-all",
            "ui-corner-bottom",
            "ui-corner-left",
            "ui-corner-top",
            "ui-icon",
            "ui-icon-flow",
            "ui-icon-plusthick",
            "ui-icon-save",
            "ui-icon-submit",
            "ui-progressbar",
            "ui-progressbar-value",
            "ui-state-default",
            "ui-tab-form-content",
            "ui-table-A",
            "ui-table-clear",
            "ui-widget",
            "ui-widget-content",
            "ui-widget-header",
            "x-fieldset",
            "x-fieldset-header"
          ],
          [
            "fn-clear",
            "img-",
            "title-r",
            "tpl-form-border",
            "tpl-form-new",
            "tpl-toolbar-new",
            "ui-tab-form-content",
            "ui-table-A",
            "x-fieldset",
            "x-fieldset-header"
          ],
          [
            "delete",
            "fileinput-button",
            "files",
            "fileupload-buttonbar",
            "fileupload-content",
            "fileupload-progressbar",
            "fn-clear",
            "img-",
            "name",
            "preview",
            "size",
            "template-download",
            "title-r",
            "tpl-form-border",
            "tpl-form-new",
            "tpl-toolbar-new",
            "ui-button",
            "ui-button-FixCS",
            "ui-button-FixCS-small",
            "ui-button-icon-only",
            "ui-button-icon-primary",
            "ui-button-text",
            "ui-button-text-icon-primary",
            "ui-corner-all",
            "ui-corner-bottom",
            "ui-corner-left",
            "ui-corner-right",
            "ui-corner-top",
            "ui-icon",
            "ui-icon-flow",
            "ui-icon-plusthick",
            "ui-icon-save",
            "ui-icon-submit",
            "ui-icon-trash",
            "ui-progressbar",
            "ui-progressbar-value",
            "ui-state-default",
            "ui-tab-form-content",
            "ui-table-A",
            "ui-table-clear",
            "ui-widget",
            "ui-widget-content",
            "ui-widget-header",
            "x-fieldset",
            "x-fieldset-header"
          ]
        ]
      }
    },
    "page/tagTriplets": {
      "contexts": {
        "context1": [
          [
            "-/-/DIV",
            "-/-/INPUT-hidden",
            "-/-/SCRIPT",
            "-/DIV/DIV",
            "-/DIV/FIELDSET",
            "A/SPAN/EM",
            "DIV/A/SPAN",
            "DIV/DIV/A",
            "DIV/DIV/DIV",
            "DIV/DIV/H1",
            "DIV/DIV/TABLE",
            "DIV/FIELDSET/LEGEND",
            "DIV/FORM/DIV",
            "DIV/H1/LABEL",
            "DIV/H1/SPAN",
            "DIV/LABEL/INPUT-file",
            "DIV/LABEL/SPAN",
            "DIV/TABLE/TBODY",
            "FIELDSET/LEGEND/B",
            "FIELDSET/LEGEND/INPUT-text",
            "FIELDSET/LEGEND/LABEL",
            "FORM/DIV/INPUT-hidden",
            "FORM/DIV/LABEL",
            "LABEL/SPAN/SPAN",
            "SPAN/DIV/DIV",
            "SPAN/DIV/FORM",
            "SPAN/SELECT/OPTION",
            "SPAN/TABLE/TBODY",
            "TABLE/TBODY/TR",
            "TBODY/TR/TD",
            "TD/DIV/A",
            "TD/KBD/SPAN",
            "TD/SPAN/DIV",
            "TD/SPAN/SELECT",
            "TD/SPAN/TABLE",
            "TR/TD/DIV",
            "TR/TD/INPUT-text",
            "TR/TD/KBD",
            "TR/TD/LABEL",
            "TR/TD/SPAN"
          ],
          [
            "-/-/DIV",
            "-/-/SCRIPT",
            "-/DIV/DIV",
            "-/DIV/FIELDSET",
            "DIV/DIV/DIV",
            "DIV/DIV/H1",
            "DIV/DIV/TABLE",
            "DIV/FIELDSET/LEGEND",
            "DIV/H1/LABEL",
            "DIV/H1/SPAN",
            "DIV/TABLE/TBODY",
            "FIELDSET/LEGEND/B",
            "FIELDSET/LEGEND/INPUT-text",
            "FIELDSET/LEGEND/LABEL",
            "TABLE/TBODY/TR",
            "TBODY/TR/TD",
            "TD/KBD/SPAN",
            "TR/TD/INPUT-text",
            "TR/TD/KBD",
            "TR/TD/LABEL",
            "TR/TD/SPAN"
          ],
          [
            "-/-/DIV",
            "-/-/INPUT-hidden",
            "-/-/SCRIPT",
            "-/DIV/DIV",
            "-/DIV/FIELDSET",
            "A/SPAN/EM",
            "DIV/A/SPAN",
            "DIV/DIV/A",
            "DIV/DIV/DIV",
            "DIV/DIV/H1",
            "DIV/DIV/TABLE",
            "DIV/FIELDSET/LEGEND",
            "DIV/FORM/DIV",
            "DIV/H1/LABEL",
            "DIV/H1/SPAN",
            "DIV/LABEL/INPUT-file",
            "DIV/LABEL/SPAN",
            "DIV/TABLE/TBODY",
            "FIELDSET/LEGEND/B",
            "FIELDSET/LEGEND/INPUT-text",
            "FIELDSET/LEGEND/LABEL",
            "FORM/DIV/INPUT-hidden",
            "FORM/DIV/LABEL",
            "LABEL/SPAN/SPAN",
            "SPAN/DIV/DIV",
            "SPAN/DIV/FORM",
            "SPAN/SELECT/OPTION",
            "SPAN/TABLE/TBODY",
            "TABLE/TBODY/TR",
            "TBODY/TR/TD",
            "TD/BUTTON/SPAN",
            "TD/DIV/A",
            "TD/KBD/SPAN",
            "TD/SPAN/DIV",
            "TD/SPAN/SELECT",
            "TD/SPAN/TABLE",
            "TR/TD/A",
            "TR/TD/BUTTON",
            "TR/TD/DIV",
            "TR/TD/INPUT-text",
            "TR/TD/KBD",
            "TR/TD/LABEL",
            "TR/TD/SPAN"
          ]
        ]
      }
    }
  }
}